[
  {
    "id": "ConcRUM_0001",
    "unit1": [
      "uns,",
      "schon"
    ],
    "frequencyLeft": 45,
    "excerpt": "willkommen Wir kennen uns schon Dann geht es los",
    "unit2": [
      "schon,",
      "dann"
    ],
    "frequencyRight": 8
  },
  {
    "id": "ConcRUM_0002",
    "unit1": [
      "habe,",
      "schon"
    ],
    "frequencyLeft": 32,
    "excerpt": "vor Ihnen Ich habe schon gesagt 2024 ist ein",
    "unit2": [
      "schon,",
      "gesagt"
    ],
    "frequencyRight": 341
  },
  {
    "id": "ConcRUM_0003",
    "unit1": [
      "gerade,",
      "schon"
    ],
    "frequencyLeft": 128,
    "excerpt": "da hatte ich gerade schon gesagt wir werden mit",
    "unit2": [
      "schon,",
      "gesagt"
    ],
    "frequencyRight": 341
  },
  {
    "id": "ConcRUM_0004",
    "unit1": [
      "wir,",
      "schon"
    ],
    "frequencyLeft": 240,
    "excerpt": "evaluieren Das haben wir schon gemacht Das auswerten Und",
    "unit2": [
      "schon,",
      "gemacht"
    ],
    "frequencyRight": 24
  },
  {
    "id": "ConcRUM_0005",
    "unit1": [
      "ist,",
      "schon"
    ],
    "frequencyLeft": 269,
    "excerpt": "nachgelagerten Behörden Es ist schon jetzt so dass 43",
    "unit2": [
      "schon,",
      "jetzt"
    ],
    "frequencyRight": 50
  },
  {
    "id": "ConcRUM_0006",
    "unit1": [
      "heute,",
      "schon"
    ],
    "frequencyLeft": 136,
    "excerpt": "Vorhaben Sie haben heute schon gesagt es werden Eckpunkte",
    "unit2": [
      "schon,",
      "gesagt"
    ],
    "frequencyRight": 341
  },
  {
    "id": "ConcRUM_0007",
    "unit1": [
      "hat,",
      "schon"
    ],
    "frequencyLeft": 53,
    "excerpt": "Demokratie Mein Ministerium hat schon lange das erkannt dass",
    "unit2": [
      "schon,",
      "lange"
    ],
    "frequencyRight": 44
  },
  {
    "id": "ConcRUM_0008",
    "unit1": [
      "vielleicht,",
      "schon"
    ],
    "frequencyLeft": 22,
    "excerpt": "die Menschen die vielleicht schon im Extremismus verfallen sind",
    "unit2": [
      "schon,",
      "im"
    ],
    "frequencyRight": 108
  },
  {
    "id": "ConcRUM_0009",
    "unit1": [
      "habe,",
      "schon"
    ],
    "frequencyLeft": 32,
    "excerpt": "15 Modellprojekten Ich habe schon angesprochen den fürchterlichen Angriff",
    "unit2": [
      "schon,",
      "angesprochen"
    ],
    "frequencyRight": 230
  },
  {
    "id": "ConcRUM_0010",
    "unit1": [
      "auch,",
      "schon"
    ],
    "frequencyLeft": 989,
    "excerpt": "ich habe eben auch schon erwähnt Entschuldigung ich habe",
    "unit2": [
      "schon,",
      "erwähnt"
    ],
    "frequencyRight": 101
  },
  {
    "id": "ConcRUM_0011",
    "unit1": [
      "auch,",
      "schon"
    ],
    "frequencyLeft": 989,
    "excerpt": "ich habe eben auch schon erwähnt dass dieses Jahr",
    "unit2": [
      "schon,",
      "erwähnt"
    ],
    "frequencyRight": 101
  },
  {
    "id": "ConcRUM_0012",
    "unit1": [
      "natürlich,",
      "schon"
    ],
    "frequencyLeft": 49,
    "excerpt": "Ministerin es ist natürlich schon erschütternd mit welcher Arroganz",
    "unit2": [
      "schon,",
      "erschütternd"
    ],
    "frequencyRight": 1
  },
  {
    "id": "ConcRUM_0013",
    "unit1": [
      "ja,",
      "schon"
    ],
    "frequencyLeft": 262,
    "excerpt": "Darauf sind Sie ja schon eingegangen Das finden wir",
    "unit2": [
      "schon,",
      "eingegangen"
    ],
    "frequencyRight": 5
  },
  {
    "id": "ConcRUM_0014",
    "unit1": [
      "bereinigungssitzung,",
      "schon"
    ],
    "frequencyLeft": 1,
    "excerpt": "Parlament in der Bereinigungssitzung schon als politische Aussage getroffen",
    "unit2": [
      "schon,",
      "als"
    ],
    "frequencyRight": 22
  },
  {
    "id": "ConcRUM_0015",
    "unit1": [
      "bericht,",
      "schon"
    ],
    "frequencyLeft": 2,
    "excerpt": "Sie auf dem Bericht schon hingewiesen Den haben wir",
    "unit2": [
      "schon,",
      "hingewiesen"
    ],
    "frequencyRight": 17
  },
  {
    "id": "ConcRUM_0016",
    "unit1": [
      "ich,",
      "schon"
    ],
    "frequencyLeft": 219,
    "excerpt": "Milliarden Euro hatte ich schon gesagt sind gesichert laufen",
    "unit2": [
      "schon,",
      "gesagt"
    ],
    "frequencyRight": 341
  },
  {
    "id": "ConcRUM_0017",
    "unit1": [
      "hier,",
      "schon"
    ],
    "frequencyLeft": 96,
    "excerpt": "dessen dass wir hier schon überzogen haben und auch",
    "unit2": [
      "schon,",
      "überzogen"
    ],
    "frequencyRight": 3
  },
  {
    "id": "ConcRUM_0018",
    "unit1": [
      "eben,",
      "schon"
    ],
    "frequencyLeft": 179,
    "excerpt": "Thema Alleinerziehende ist eben schon gefallen Wir haben es",
    "unit2": [
      "schon,",
      "gefallen"
    ],
    "frequencyRight": 10
  },
  {
    "id": "ConcRUM_0019",
    "unit1": [
      "auch,",
      "schon"
    ],
    "frequencyLeft": 989,
    "excerpt": "anderes Thema ist auch schon länger ein Dauerbrenner Auch",
    "unit2": [
      "schon,",
      "länger"
    ],
    "frequencyRight": 25
  },
  {
    "id": "ConcRUM_0020",
    "unit1": [
      "auch,",
      "schon"
    ],
    "frequencyLeft": 989,
    "excerpt": "in Ihrer Vorhabenplanung auch schon für das Jahr 2024",
    "unit2": [
      "schon,",
      "für"
    ],
    "frequencyRight": 42
  },
  {
    "id": "ConcRUM_0021",
    "unit1": [
      "sie,",
      "schon"
    ],
    "frequencyLeft": 95,
    "excerpt": "Zusammenhang das haben Sie schon angerissen natürlich auch dass",
    "unit2": [
      "schon,",
      "angerissen"
    ],
    "frequencyRight": 6
  },
  {
    "id": "ConcRUM_0022",
    "unit1": [
      "einführend,",
      "schon"
    ],
    "frequencyLeft": 1,
    "excerpt": "Dank Wie ich einführend schon gesagt habe ist mir",
    "unit2": [
      "schon,",
      "gesagt"
    ],
    "frequencyRight": 341
  },
  {
    "id": "ConcRUM_0023",
    "unit1": [
      "stelle,",
      "schon"
    ],
    "frequencyLeft": 10,
    "excerpt": "Antwort an der Stelle schon mal Ich glaube Sie",
    "unit2": [
      "schon,",
      "mal"
    ],
    "frequencyRight": 372
  },
  {
    "id": "ConcRUM_0024",
    "unit1": [
      "auch,",
      "schon"
    ],
    "frequencyLeft": 989,
    "excerpt": "den Sie gerade auch schon angesprochen haben gerne noch",
    "unit2": [
      "schon,",
      "angesprochen"
    ],
    "frequencyRight": 230
  },
  {
    "id": "ConcRUM_0025",
    "unit1": [
      "nicht,",
      "schon"
    ],
    "frequencyLeft": 23,
    "excerpt": "abzuholen dass sie nicht schon jetzt in ihrer analogen",
    "unit2": [
      "schon,",
      "jetzt"
    ],
    "frequencyRight": 50
  },
  {
    "id": "ConcRUM_0026",
    "unit1": [
      "auch,",
      "schon"
    ],
    "frequencyLeft": 989,
    "excerpt": "es eventuell ja auch schon ganz gute Projekte die",
    "unit2": [
      "schon,",
      "ganz"
    ],
    "frequencyRight": 36
  },
  {
    "id": "ConcRUM_0027",
    "unit1": [
      "gerade,",
      "schon"
    ],
    "frequencyLeft": 128,
    "excerpt": "nichts Es wurde gerade schon angesprochen MentalHealthCoaches und das",
    "unit2": [
      "schon,",
      "angesprochen"
    ],
    "frequencyRight": 230
  },
  {
    "id": "ConcRUM_0028",
    "unit1": [
      "nachdem,",
      "schon"
    ],
    "frequencyLeft": 3,
    "excerpt": "deswegen meine Frage nachdem schon viele Bündnispartner aus ihrem",
    "unit2": [
      "schon,",
      "viele"
    ],
    "frequencyRight": 25
  },
  {
    "id": "ConcRUM_0029",
    "unit1": [
      "auch,",
      "schon"
    ],
    "frequencyLeft": 989,
    "excerpt": "Das wäre ja auch schon was freiwillig auf zwei",
    "unit2": [
      "schon,",
      "was"
    ],
    "frequencyRight": 38
  },
  {
    "id": "ConcRUM_0030",
    "unit1": [
      "ist,",
      "schon"
    ],
    "frequencyLeft": 269,
    "excerpt": "Mental Health Coaches ist schon gefallen Laut Ihrer Vorhabenplanung",
    "unit2": [
      "schon,",
      "gefallen"
    ],
    "frequencyRight": 10
  },
  {
    "id": "ConcRUM_0031",
    "unit1": [
      "auch,",
      "schon"
    ],
    "frequencyLeft": 989,
    "excerpt": "als Ministerin sind auch schon lange dran Wir stehen",
    "unit2": [
      "schon,",
      "lange"
    ],
    "frequencyRight": 44
  },
  {
    "id": "ConcRUM_0032",
    "unit1": [
      "sozusagen,",
      "schon"
    ],
    "frequencyLeft": 6,
    "excerpt": "Manche haben auch sozusagen schon angefangen daran zu zweifeln",
    "unit2": [
      "schon,",
      "angefangen"
    ],
    "frequencyRight": 5
  },
  {
    "id": "ConcRUM_0033",
    "unit1": [
      "verhandlungsstand,",
      "schon"
    ],
    "frequencyLeft": 1,
    "excerpt": "da ist der Verhandlungsstand schon sehr weit Kann ich",
    "unit2": [
      "schon,",
      "sehr"
    ],
    "frequencyRight": 166
  },
  {
    "id": "ConcRUM_0034",
    "unit1": [
      "da,",
      "schon"
    ],
    "frequencyLeft": 95,
    "excerpt": "nachreichen Wir sind da schon sehr weit Die Aufbaugeschichte",
    "unit2": [
      "schon,",
      "sehr"
    ],
    "frequencyRight": 166
  },
  {
    "id": "ConcRUM_0035",
    "unit1": [
      "hatten,",
      "schon"
    ],
    "frequencyLeft": 16,
    "excerpt": "ähnliche Richtung Wir hatten schon angesprochen dass es für",
    "unit2": [
      "schon,",
      "angesprochen"
    ],
    "frequencyRight": 230
  },
  {
    "id": "ConcRUM_0036",
    "unit1": [
      "ja,",
      "schon"
    ],
    "frequencyLeft": 262,
    "excerpt": "Termine Es wurden ja schon einige Termine genannt Wie",
    "unit2": [
      "schon,",
      "einige"
    ],
    "frequencyRight": 35
  },
  {
    "id": "ConcRUM_0037",
    "unit1": [
      "das,",
      "schon"
    ],
    "frequencyLeft": 176,
    "excerpt": "wenn sie denn das schon nicht auf EUEbene verteidigen",
    "unit2": [
      "schon,",
      "nicht"
    ],
    "frequencyRight": 21
  },
  {
    "id": "ConcRUM_0038",
    "unit1": [
      "auch,",
      "schon"
    ],
    "frequencyLeft": 989,
    "excerpt": "ich habe es auch schon mal dargestellt dass die",
    "unit2": [
      "schon,",
      "mal"
    ],
    "frequencyRight": 372
  },
  {
    "id": "ConcRUM_0039",
    "unit1": [
      "auch,",
      "schon"
    ],
    "frequencyLeft": 989,
    "excerpt": "alt nur manchmal auch schon zehn oder zwölf Die",
    "unit2": [
      "schon,",
      "zehn"
    ],
    "frequencyRight": 7
  },
  {
    "id": "ConcRUM_0040",
    "unit1": [
      "auch,",
      "schon"
    ],
    "frequencyLeft": 989,
    "excerpt": "die Berichte die auch schon vorliegen in der Datenbank",
    "unit2": [
      "schon,",
      "vorliegen"
    ],
    "frequencyRight": 2
  },
  {
    "id": "ConcRUM_0041",
    "unit1": [
      "teil,",
      "schon"
    ],
    "frequencyLeft": 12,
    "excerpt": "gibt es zum Teil schon sehr viel länger Sie",
    "unit2": [
      "schon,",
      "sehr"
    ],
    "frequencyRight": 166
  },
  {
    "id": "ConcRUM_0042",
    "unit1": [
      "ich,",
      "schon"
    ],
    "frequencyLeft": 219,
    "excerpt": "Aufsichtsstrukturen darauf hatte ich schon hingewiesen sind sehr wichtig",
    "unit2": [
      "schon,",
      "hingewiesen"
    ],
    "frequencyRight": 17
  },
  {
    "id": "ConcRUM_0043",
    "unit1": [
      "auch,",
      "schon"
    ],
    "frequencyLeft": 989,
    "excerpt": "dann bin ich auch schon fertig Hier sehen Sie",
    "unit2": [
      "schon,",
      "fertig"
    ],
    "frequencyRight": 6
  },
  {
    "id": "ConcRUM_0044",
    "unit1": [
      "kinder,",
      "schon"
    ],
    "frequencyLeft": 4,
    "excerpt": "habe zwei erwachsene Kinder schon Selbst habe ich an",
    "unit2": [
      "schon,",
      "selbst"
    ],
    "frequencyRight": 5
  },
  {
    "id": "ConcRUM_0045",
    "unit1": [
      "wie,",
      "schon"
    ],
    "frequencyLeft": 60,
    "excerpt": "für sechs Wochen wie schon vorher gehört im Alter",
    "unit2": [
      "schon,",
      "vorher"
    ],
    "frequencyRight": 28
  },
  {
    "id": "ConcRUM_0046",
    "unit1": [
      "auch,",
      "schon"
    ],
    "frequencyLeft": 989,
    "excerpt": "ohne Kontakt wie auch schon gehört zu meinen Eltern",
    "unit2": [
      "schon,",
      "gehört"
    ],
    "frequencyRight": 138
  },
  {
    "id": "ConcRUM_0047",
    "unit1": [
      "hat,",
      "schon"
    ],
    "frequencyLeft": 53,
    "excerpt": "Information meiner Vorredner hat schon gezeigt dass die Aufgabe",
    "unit2": [
      "schon,",
      "gezeigt"
    ],
    "frequencyRight": 4
  },
  {
    "id": "ConcRUM_0048",
    "unit1": [
      "was,",
      "schon"
    ],
    "frequencyLeft": 33,
    "excerpt": "uns Stichwort Bürgerforschung was schon erwähnt wurde Diese zentrale",
    "unit2": [
      "schon,",
      "erwähnt"
    ],
    "frequencyRight": 101
  },
  {
    "id": "ConcRUM_0049",
    "unit1": [
      "jahre,",
      "schon"
    ],
    "frequencyLeft": 4,
    "excerpt": "Arbeit über die Jahre schon investiert haben Und viele",
    "unit2": [
      "schon,",
      "investiert"
    ],
    "frequencyRight": 1
  },
  {
    "id": "ConcRUM_0050",
    "unit1": [
      "eben,",
      "schon"
    ],
    "frequencyLeft": 179,
    "excerpt": "Sie haben das eben schon gut geschildert das einer",
    "unit2": [
      "schon,",
      "gut"
    ],
    "frequencyRight": 17
  },
  {
    "id": "ConcRUM_0051",
    "unit1": [
      "dann,",
      "schon"
    ],
    "frequencyLeft": 58,
    "excerpt": "BundesbahnSonderzüge Das waren dann schon im Jahr 390 Das",
    "unit2": [
      "schon,",
      "im"
    ],
    "frequencyRight": 108
  },
  {
    "id": "ConcRUM_0052",
    "unit1": [
      "wir,",
      "schon"
    ],
    "frequencyLeft": 240,
    "excerpt": "Herrn Nützenagel haben wir schon 2000 Heime und nicht",
    "unit2": [
      "schon,",
      "2000"
    ],
    "frequencyRight": 1
  },
  {
    "id": "ConcRUM_0053",
    "unit1": [
      "wir,",
      "schon"
    ],
    "frequencyLeft": 240,
    "excerpt": "niedrigsten Zahl haben wir schon ermittelt für zehn Jahre",
    "unit2": [
      "schon,",
      "ermittelt"
    ],
    "frequencyRight": 1
  },
  {
    "id": "ConcRUM_0054",
    "unit1": [
      "eben,",
      "schon"
    ],
    "frequencyLeft": 179,
    "excerpt": "uns Sie hatten eben schon was zu den Schätzungen",
    "unit2": [
      "schon,",
      "was"
    ],
    "frequencyRight": 38
  },
  {
    "id": "ConcRUM_0055",
    "unit1": [
      "der,",
      "schon"
    ],
    "frequencyLeft": 32,
    "excerpt": "bisher einen Fragebogen der schon 15000 Mal vollständig ausgefüllt",
    "unit2": [
      "schon,",
      "15000"
    ],
    "frequencyRight": 1
  },
  {
    "id": "ConcRUM_0056",
    "unit1": [
      "jetzt,",
      "schon"
    ],
    "frequencyLeft": 331,
    "excerpt": "Facebook gibt es jetzt schon mehrere Gruppen die sich",
    "unit2": [
      "schon,",
      "mehrere"
    ],
    "frequencyRight": 7
  },
  {
    "id": "ConcRUM_0057",
    "unit1": [
      "natürlich,",
      "schon"
    ],
    "frequencyLeft": 49,
    "excerpt": "sondern das sind natürlich schon Aufarbeitungsprojekte die in einem",
    "unit2": [
      "schon,",
      "aufarbeitungsprojekte"
    ],
    "frequencyRight": 1
  },
  {
    "id": "ConcRUM_0058",
    "unit1": [
      "jetzt,",
      "schon"
    ],
    "frequencyLeft": 331,
    "excerpt": "so wie das jetzt schon bei uns ehrenamtlich läuft",
    "unit2": [
      "schon,",
      "bei"
    ],
    "frequencyRight": 65
  },
  {
    "id": "ConcRUM_0059",
    "unit1": [
      "dazu,",
      "schon"
    ],
    "frequencyLeft": 15,
    "excerpt": "in NRW hat dazu schon eine Studie begonnen Nur",
    "unit2": [
      "schon,",
      "eine"
    ],
    "frequencyRight": 159
  },
  {
    "id": "ConcRUM_0060",
    "unit1": [
      "es,",
      "schon"
    ],
    "frequencyLeft": 212,
    "excerpt": "Herr Udeclau hat es schon gesagt Aber ich würde",
    "unit2": [
      "schon,",
      "gesagt"
    ],
    "frequencyRight": 341
  },
  {
    "id": "ConcRUM_0061",
    "unit1": [
      "natürlich,",
      "schon"
    ],
    "frequencyLeft": 49,
    "excerpt": "Und da ist natürlich schon die Erfahrung zu sehen",
    "unit2": [
      "schon,",
      "die"
    ],
    "frequencyRight": 185
  },
  {
    "id": "ConcRUM_0062",
    "unit1": [
      "sozusagen,",
      "schon"
    ],
    "frequencyLeft": 6,
    "excerpt": "mit den Trägern sozusagen schon ehrenamtlich gegründet ins Leben",
    "unit2": [
      "schon,",
      "ehrenamtlich"
    ],
    "frequencyRight": 1
  },
  {
    "id": "ConcRUM_0063",
    "unit1": [
      "eben,",
      "schon"
    ],
    "frequencyLeft": 179,
    "excerpt": "Und das hat eben schon Herr Rüttgenklau aufgeklärt wie",
    "unit2": [
      "schon,",
      "herr"
    ],
    "frequencyRight": 5
  },
  {
    "id": "ConcRUM_0064",
    "unit1": [
      "röhl,",
      "schon"
    ],
    "frequencyLeft": 1,
    "excerpt": "bestätigen was Frau Röhl schon gesagt hat Wir wissen",
    "unit2": [
      "schon,",
      "gesagt"
    ],
    "frequencyRight": 341
  },
  {
    "id": "ConcRUM_0065",
    "unit1": [
      "der,",
      "schon"
    ],
    "frequencyLeft": 32,
    "excerpt": "für einen Austausch der schon ein paar Wochen zurückliegt",
    "unit2": [
      "schon,",
      "ein"
    ],
    "frequencyRight": 208
  },
  {
    "id": "ConcRUM_0066",
    "unit1": [
      "auch,",
      "schon"
    ],
    "frequencyLeft": 989,
    "excerpt": "beginnen was ich auch schon in der letzten Austauschrunde",
    "unit2": [
      "schon,",
      "in"
    ],
    "frequencyRight": 212
  },
  {
    "id": "ConcRUM_0067",
    "unit1": [
      "auch,",
      "schon"
    ],
    "frequencyLeft": 989,
    "excerpt": "zum einen was auch schon angesprochen wurde von Herrn",
    "unit2": [
      "schon,",
      "angesprochen"
    ],
    "frequencyRight": 230
  },
  {
    "id": "ConcRUM_0068",
    "unit1": [
      "gerade,",
      "schon"
    ],
    "frequencyLeft": 128,
    "excerpt": "anderen Fragen wurden gerade schon gestellt bezüglich der Aufsichtspflicht",
    "unit2": [
      "schon,",
      "gestellt"
    ],
    "frequencyRight": 7
  },
  {
    "id": "ConcRUM_0069",
    "unit1": [
      "ich,",
      "schon"
    ],
    "frequencyLeft": 219,
    "excerpt": "hat da habe ich schon 2019 einen Film durch",
    "unit2": [
      "schon,",
      "2019"
    ],
    "frequencyRight": 2
  },
  {
    "id": "ConcRUM_0070",
    "unit1": [
      "thema,",
      "schon"
    ],
    "frequencyLeft": 9,
    "excerpt": "Ich begleite dieses Thema schon seit der letzten Wahlperiode",
    "unit2": [
      "schon,",
      "seit"
    ],
    "frequencyRight": 111
  },
  {
    "id": "ConcRUM_0071",
    "unit1": [
      "auch,",
      "schon"
    ],
    "frequencyLeft": 989,
    "excerpt": "da habe ich auch schon diverse Ministerien angeschrieben und",
    "unit2": [
      "schon,",
      "diverse"
    ],
    "frequencyRight": 2
  },
  {
    "id": "ConcRUM_0072",
    "unit1": [
      "auch,",
      "schon"
    ],
    "frequencyLeft": 989,
    "excerpt": "der letzten Wahlperiode auch schon erlebt Und am Ende",
    "unit2": [
      "schon,",
      "erlebt"
    ],
    "frequencyRight": 6
  },
  {
    "id": "ConcRUM_0073",
    "unit1": [
      "eben,",
      "schon"
    ],
    "frequencyLeft": 179,
    "excerpt": "das habe ich eben schon anklingen lassen was müssen",
    "unit2": [
      "schon,",
      "anklingen"
    ],
    "frequencyRight": 3
  },
  {
    "id": "ConcRUM_0074",
    "unit1": [
      "auch,",
      "schon"
    ],
    "frequencyLeft": 989,
    "excerpt": "Aber es ist auch schon so dass es auch",
    "unit2": [
      "schon,",
      "so"
    ],
    "frequencyRight": 77
  },
  {
    "id": "ConcRUM_0075",
    "unit1": [
      "aufarbeitung,",
      "schon"
    ],
    "frequencyLeft": 1,
    "excerpt": "Dinge wo eine Aufarbeitung schon gemacht worden ist oder",
    "unit2": [
      "schon,",
      "gemacht"
    ],
    "frequencyRight": 24
  },
  {
    "id": "ConcRUM_0076",
    "unit1": [
      "auch,",
      "schon"
    ],
    "frequencyLeft": 989,
    "excerpt": "sich mit denen auch schon Es ist doch ein",
    "unit2": [
      "schon,",
      "es"
    ],
    "frequencyRight": 13
  },
  {
    "id": "ConcRUM_0077",
    "unit1": [
      "heimerziehung,",
      "schon"
    ],
    "frequencyLeft": 1,
    "excerpt": "einem Professor für Heimerziehung schon bevor die ganze Initiative",
    "unit2": [
      "schon,",
      "bevor"
    ],
    "frequencyRight": 5
  },
  {
    "id": "ConcRUM_0078",
    "unit1": [
      "wieghofer,",
      "schon"
    ],
    "frequencyLeft": 1,
    "excerpt": "zum Beispiel in Wieghofer schon Akten gefunden wo von",
    "unit2": [
      "schon,",
      "akten"
    ],
    "frequencyRight": 1
  },
  {
    "id": "ConcRUM_0079",
    "unit1": [
      "adolfinenheim,",
      "schon"
    ],
    "frequencyLeft": 1,
    "excerpt": "Aufsatz für das Adolfinenheim schon belegt Die Heime hatten",
    "unit2": [
      "schon,",
      "belegt"
    ],
    "frequencyRight": 1
  },
  {
    "id": "ConcRUM_0080",
    "unit1": [
      "es,",
      "schon"
    ],
    "frequencyLeft": 212,
    "excerpt": "Ja da gab es schon Und deswegen ist das",
    "unit2": [
      "schon,",
      "und"
    ],
    "frequencyRight": 28
  },
  {
    "id": "ConcRUM_0081",
    "unit1": [
      "gerade,",
      "schon"
    ],
    "frequencyLeft": 128,
    "excerpt": "Sie haben das gerade schon ein bisschen skizziert Aber",
    "unit2": [
      "schon,",
      "ein"
    ],
    "frequencyRight": 208
  },
  {
    "id": "ConcRUM_0082",
    "unit1": [
      "wirkungen,",
      "schon"
    ],
    "frequencyLeft": 1,
    "excerpt": "Also waren die Wirkungen schon sehr nachhaltig Und meine",
    "unit2": [
      "schon,",
      "sehr"
    ],
    "frequencyRight": 166
  },
  {
    "id": "ConcRUM_0083",
    "unit1": [
      "auch,",
      "schon"
    ],
    "frequencyLeft": 989,
    "excerpt": "in diesem Zusammenhang auch schon mal mit der OBSKM",
    "unit2": [
      "schon,",
      "mal"
    ],
    "frequencyRight": 372
  },
  {
    "id": "ConcRUM_0084",
    "unit1": [
      "auch,",
      "schon"
    ],
    "frequencyLeft": 989,
    "excerpt": "Und der ist auch schon der wird schon diskutiert",
    "unit2": [
      "schon,",
      "der"
    ],
    "frequencyRight": 40
  },
  {
    "id": "ConcRUM_0085",
    "unit1": [
      "wird,",
      "schon"
    ],
    "frequencyLeft": 21,
    "excerpt": "auch schon der wird schon diskutiert Aber die Balneologie",
    "unit2": [
      "schon,",
      "diskutiert"
    ],
    "frequencyRight": 21
  },
  {
    "id": "ConcRUM_0086",
    "unit1": [
      "dann,",
      "schon"
    ],
    "frequencyLeft": 58,
    "excerpt": "durch die Leberwerte dann schon runtergenommen wurden Die Medikamente",
    "unit2": [
      "schon,",
      "runtergenommen"
    ],
    "frequencyRight": 1
  },
  {
    "id": "ConcRUM_0087",
    "unit1": [
      "hatte,",
      "schon"
    ],
    "frequencyLeft": 20,
    "excerpt": "immer sozusagen Es hatte schon auch soziale Hintergründe oder",
    "unit2": [
      "schon,",
      "auch"
    ],
    "frequencyRight": 105
  },
  {
    "id": "ConcRUM_0088",
    "unit1": [
      "da,",
      "schon"
    ],
    "frequencyLeft": 95,
    "excerpt": "sehen überfraktionell ist da schon die Betroffenheit auf jeden",
    "unit2": [
      "schon,",
      "die"
    ],
    "frequencyRight": 185
  },
  {
    "id": "ConcRUM_0089",
    "unit1": [
      "uns,",
      "schon"
    ],
    "frequencyLeft": 45,
    "excerpt": "vorschlagen dass wir uns schon die Zeit nehmen einmal",
    "unit2": [
      "schon,",
      "die"
    ],
    "frequencyRight": 185
  },
  {
    "id": "ConcRUM_0090",
    "unit1": [
      "es,",
      "schon"
    ],
    "frequencyLeft": 212,
    "excerpt": "Frau Thiemann hat es schon angedeutet Ein überdurchschnittlicher Anteil",
    "unit2": [
      "schon,",
      "angedeutet"
    ],
    "frequencyRight": 44
  },
  {
    "id": "ConcRUM_0091",
    "unit1": [
      "das,",
      "schon"
    ],
    "frequencyLeft": 176,
    "excerpt": "Frau Thiesen hatte das schon angedeutet Wir halten das",
    "unit2": [
      "schon,",
      "angedeutet"
    ],
    "frequencyRight": 44
  },
  {
    "id": "ConcRUM_0092",
    "unit1": [
      "erwerbsarbeit,",
      "schon"
    ],
    "frequencyLeft": 1,
    "excerpt": "die Care und Erwerbsarbeit schon vor der Trennung annähernd",
    "unit2": [
      "schon,",
      "vor"
    ],
    "frequencyRight": 67
  },
  {
    "id": "ConcRUM_0093",
    "unit1": [
      "thiemann,",
      "schon"
    ],
    "frequencyLeft": 1,
    "excerpt": "Hier hatte Frau Thiemann schon darauf hingewiesen dass Alleinerziehende",
    "unit2": [
      "schon,",
      "darauf"
    ],
    "frequencyRight": 34
  },
  {
    "id": "ConcRUM_0094",
    "unit1": [
      "auch,",
      "schon"
    ],
    "frequencyLeft": 989,
    "excerpt": "Da kam ja auch schon viel von meinen Vorrednerinnen",
    "unit2": [
      "schon,",
      "viel"
    ],
    "frequencyRight": 46
  },
  {
    "id": "ConcRUM_0095",
    "unit1": [
      "zumindest,",
      "schon"
    ],
    "frequencyLeft": 5,
    "excerpt": "in der Anwaltschaft zumindest schon häufig sehen dass es",
    "unit2": [
      "schon,",
      "häufig"
    ],
    "frequencyRight": 6
  },
  {
    "id": "ConcRUM_0096",
    "unit1": [
      "sich,",
      "schon"
    ],
    "frequencyLeft": 73,
    "excerpt": "wird dass sie sich schon überlegen kann ich diesen",
    "unit2": [
      "schon,",
      "überlegen"
    ],
    "frequencyRight": 3
  },
  {
    "id": "ConcRUM_0097",
    "unit1": [
      "da,",
      "schon"
    ],
    "frequencyLeft": 95,
    "excerpt": "lange Also dass da schon eine Tendenz da ist",
    "unit2": [
      "schon,",
      "eine"
    ],
    "frequencyRight": 159
  },
  {
    "id": "ConcRUM_0098",
    "unit1": [
      "jetzt,",
      "schon"
    ],
    "frequencyLeft": 331,
    "excerpt": "an das was jetzt schon gesagt worden ist noch",
    "unit2": [
      "schon,",
      "gesagt"
    ],
    "frequencyRight": 341
  },
  {
    "id": "ConcRUM_0099",
    "unit1": [
      "eben,",
      "schon"
    ],
    "frequencyLeft": 179,
    "excerpt": "das was Sie eben schon gesagt haben Was muss",
    "unit2": [
      "schon,",
      "gesagt"
    ],
    "frequencyRight": 341
  },
  {
    "id": "ConcRUM_0100",
    "unit1": [
      "sicht,",
      "schon"
    ],
    "frequencyLeft": 6,
    "excerpt": "es aus unserer Sicht schon so dass es Probleme",
    "unit2": [
      "schon,",
      "so"
    ],
    "frequencyRight": 77
  }
]
